bzon/__init__.py
bzon/main.py
bzon/common/__init__.py
bzon/common/func.py
bzon/common/password.py
bzon/tasks/__init__.py
bzon/tasks/hello.py
bzon/tasks/make_markdown.py
bzon/tasks/open.py
bzon/tasks/take_asin.py
bzon/tasks/tidy_title.py
beni_amazon-0.0.11.dist-info/METADATA
beni_amazon-0.0.11.dist-info/WHEEL
beni_amazon-0.0.11.dist-info/entry_points.txt
beni_amazon-0.0.11.dist-info/top_level.txt
beni_amazon-0.0.11.dist-info/RECORD
