Metadata-Version: 2.4
Name: beni-amazon
Version: 0.0.11
Summary: Commands for Beni
Author-email: Beni Mang <benimang@126.com>
Maintainer-email: Beni Mang <benimang@126.com>
Keywords: benimang,beni,beni-amazon
Requires-Python: >=3.10
Requires-Dist: beautifulsoup4
Requires-Dist: benimang==0.7.13
Requires-Dist: typer
